avutil/__init__.py
avutil/info.py
avutil/tidy_up.py
avutil/util.py
avutil/video.py
avutil/encoder/__init__.py
avutil/encoder/nfo.py
avutil/encoder/vsmeta.py
avutil/source/__init__.py
avutil/source/bus.py
avutil/source/library.py
avutil-1.6.3.data/scripts/tidy_up.py
avutil-1.6.3.dist-info/LICENSE
avutil-1.6.3.dist-info/METADATA
avutil-1.6.3.dist-info/WHEEL
avutil-1.6.3.dist-info/entry_points.txt
avutil-1.6.3.dist-info/top_level.txt
avutil-1.6.3.dist-info/RECORD
