Metadata-Version: 2.1
Name: avutil
Version: 1.6.3
Summary: Provide some useful util functions and a poweful tool (tidyup) for tidying up your video folder
Author: Everyone
Classifier: Programming Language :: Python :: 3
Classifier: License :: OSI Approved :: GNU General Public License v3 (GPLv3)
Classifier: Operating System :: OS Independent
Requires-Python: >=3.4.0
License-File: LICENSE
Requires-Dist: beautifulsoup4 >=4.7.0
Requires-Dist: requests >=2.21.0
Requires-Dist: pytesseract >=0.3.7
Requires-Dist: bitstring >=3.1.0
